<?xml version="1.0" encoding="utf-8" ?>
<dwsync>
<file name="Anhorigcentrum.png" server="srv01604f.vasteras.se/inetpub/wwwroot/" local="131207519184157352" remote="130927032000000000" Dst="2" />
<file name="Bad.png" server="srv01604f.vasteras.se/inetpub/wwwroot/" local="131207519184337370" remote="130927032000000000" Dst="2" />
<file name="Bibliotek.png" server="srv01604f.vasteras.se/inetpub/wwwroot/" local="131207519184357372" remote="130927032000000000" Dst="2" />
<file name="Boende_for_aldre.png" server="srv01604f.vasteras.se/inetpub/wwwroot/" local="131207519184547391" remote="130927032000000000" Dst="2" />
<file name="Boende_for_missbrukare.png" server="srv01604f.vasteras.se/inetpub/wwwroot/" local="131207519184567393" remote="130927032000000000" Dst="2" />
<file name="Boende_for_personer_med_funktionsnedsattning.png" server="srv01604f.vasteras.se/inetpub/wwwroot/" local="131207519184937430" remote="130927032000000000" Dst="2" />
<file name="Dagverksamhet.png" server="srv01604f.vasteras.se/inetpub/wwwroot/" local="131207519185247461" remote="130927032000000000" Dst="2" />
<file name="Familjecentrum.png" server="srv01604f.vasteras.se/inetpub/wwwroot/" local="131207519185267463" remote="130927032000000000" Dst="2" />
<file name="Forskoleverksamhet.png" server="srv01604f.vasteras.se/inetpub/wwwroot/" local="131207519185517488" remote="130927032000000000" Dst="2" />
<file name="farg.png" server="srv01604f.vasteras.se/inetpub/wwwroot/" local="131207519185277464" remote="130927032000000000" Dst="2" />
<file name="Forskoleverksamhet_24.png" server="srv01604f.vasteras.se/inetpub/wwwroot/" local="131207519185537490" remote="130927032000000000" Dst="2" />
<file name="Forskoleverksamhet_droppe.png" server="srv01604f.vasteras.se/inetpub/wwwroot/" local="131207519185597496" remote="130927032000000000" Dst="2" />
<file name="Forskoleverksamhet_kluster.png" server="srv01604f.vasteras.se/inetpub/wwwroot/" local="131207519185867523" remote="130927032000000000" Dst="2" />
<file name="Forskoleverksamhet_skugga.png" server="srv01604f.vasteras.se/inetpub/wwwroot/" local="131207519186027539" remote="130927032000000000" Dst="2" />
<file name="Fritidsgard.png" server="srv01604f.vasteras.se/inetpub/wwwroot/" local="131207519186007537" remote="130927032000000000" Dst="2" />
<file name="Fritidsverksamhet.png" server="srv01604f.vasteras.se/inetpub/wwwroot/" local="131207519186277564" remote="130927032000000000" Dst="2" />
<file name="gra.png" server="srv01604f.vasteras.se/inetpub/wwwroot/" local="131207519186407577" remote="130927032000000000" Dst="2" />
<file name="Gra_14.png" server="srv01604f.vasteras.se/inetpub/wwwroot/" local="131207519186417578" remote="130927032000000000" Dst="2" />
<file name="Grundskola_droppe.png" server="srv01604f.vasteras.se/inetpub/wwwroot/" local="131207519186717608" remote="130927032000000000" Dst="2" />
<file name="Grundskola.png" server="srv01604f.vasteras.se/inetpub/wwwroot/" local="131207519186707607" remote="130927032000000000" Dst="2" />
<file name="Idrottsanlaggningar.png" server="srv01604f.vasteras.se/inetpub/wwwroot/" local="131207519187217658" remote="130927032000000000" Dst="2" />
<file name="Grundskola_skugga.png" server="srv01604f.vasteras.se/inetpub/wwwroot/" local="131207519186737610" remote="130927032000000000" Dst="2" />
<file name="Gymnasieskola.png" server="srv01604f.vasteras.se/inetpub/wwwroot/" local="131207519187207657" remote="130927032000000000" Dst="2" />
<file name="Logga.png" server="srv01604f.vasteras.se/inetpub/wwwroot/" local="131207519187487685" remote="130927032000000000" Dst="2" />
<file name="Motionsspar.png" server="srv01604f.vasteras.se/inetpub/wwwroot/" local="131207519187737710" remote="130927032000000000" Dst="2" />
<file name="Motesplatser_for_aldre.png" server="srv01604f.vasteras.se/inetpub/wwwroot/" local="131207519187507687" remote="130927032000000000" Dst="2" />
<file name="Museum.png" server="srv01604f.vasteras.se/inetpub/wwwroot/" local="131207519187747711" remote="130927032000000000" Dst="2" />
<file name="Orange_14.png" server="srv01604f.vasteras.se/inetpub/wwwroot/" local="131207519187767713" remote="130927032000000000" Dst="2" />
<file name="orto.png" server="srv01604f.vasteras.se/inetpub/wwwroot/" local="131207519188027739" remote="130927032000000000" Dst="2" />
<file name="Sarskola.png" server="srv01604f.vasteras.se/inetpub/wwwroot/" local="131207519188067743" remote="130927032000000000" Dst="2" />
<file name="Parker.png" server="srv01604f.vasteras.se/inetpub/wwwroot/" local="131207519188027739" remote="130927032000000000" Dst="2" />
<file name="Svart_12.png" server="srv01604f.vasteras.se/inetpub/wwwroot/" local="131207519188277764" remote="130927032000000000" Dst="2" />
<file name="Svart_14.png" server="srv01604f.vasteras.se/inetpub/wwwroot/" local="131207519188287765" remote="130927032000000000" Dst="2" />
<file name="Svart_16.png" server="srv01604f.vasteras.se/inetpub/wwwroot/" local="131207519188307767" remote="130927032000000000" Dst="2" />
<file name="Vuxenutbildning.png" server="srv01604f.vasteras.se/inetpub/wwwroot/" local="131207519188857822" remote="130927032000000000" Dst="2" />
<file name="Traffpunkter.png" server="srv01604f.vasteras.se/inetpub/wwwroot/" local="131207519188557792" remote="130927032000000000" Dst="2" />
<file name="Isbanor.png" server="srv01604f.vasteras.se/inetpub/wwwroot/" local="131207519187237660" remote="130975416000000000" Dst="2" />
<file name="Lekplatser.png" server="srv01604f.vasteras.se/inetpub/wwwroot/" local="131207519187477684" remote="131045400000000000" Dst="2" />
<file name="Trygghetspunkt.png" server="srv01604f.vasteras.se/inetpub/wwwroot/" local="131207519188637800" remote="131073048000000000" Dst="2" />
</dwsync>